nysmix/__init__.py
nysmix/app/__init__.py
nysmix/app/main.py
nysmix/base.py
nysmix/concepts.py
nysmix/config.py
nysmix/data.py
nysmix/db.py
nysmix/repository.py
nysmix/schema.py
nysmix/settings.py
nysmix/utils.py
nysmix-0.10.0.dist-info/LICENSE
nysmix-0.10.0.dist-info/METADATA
nysmix-0.10.0.dist-info/WHEEL
nysmix-0.10.0.dist-info/RECORD
