Metadata-Version: 2.1
Name: nysmix
Version: 0.10.0
Summary: pulling nys fuel mix data from nysiso
Author: Gautam Sisodia
Author-email: gautam.sisodia@gmail.com
Requires-Python: >=3.11,<4.0
Classifier: Programming Language :: Python :: 3
Classifier: Programming Language :: Python :: 3.11
Provides-Extra: book
Provides-Extra: google
Provides-Extra: test
Requires-Dist: altair (>=4.2.0,<5.0.0) ; extra == "book"
Requires-Dist: autodocsumm (>=0.2.10,<0.3.0) ; extra == "book"
Requires-Dist: fastapi (>=0.89.1,<0.90.0)
Requires-Dist: fs-gcsfs (>=1.5.1,<2.0.0) ; extra == "google"
Requires-Dist: jupyter-book (>=0.13.0,<0.14.0) ; extra == "book"
Requires-Dist: jupytext (>=1.14.0,<2.0.0) ; extra == "book"
Requires-Dist: pandera (>=0.13.4,<0.14.0)
Requires-Dist: psycopg2[binary] (>=2.9.5,<3.0.0)
Requires-Dist: pyarrow (>=11.0.0,<12.0.0)
Requires-Dist: pydantic (>=1.10.1,<2.0.0)
Requires-Dist: pytest (>=7.1.2,<8.0.0) ; extra == "test"
Requires-Dist: sqlmodel (>=0.0.8,<0.0.9)
Requires-Dist: uvicorn[standard] (>=0.20.0,<0.21.0)
